dcos_metronome-0.3.0.dist-info/DESCRIPTION.rst
dcos_metronome-0.3.0.dist-info/METADATA
dcos_metronome-0.3.0.dist-info/RECORD
dcos_metronome-0.3.0.dist-info/WHEEL
dcos_metronome-0.3.0.dist-info/metadata.json
dcos_metronome-0.3.0.dist-info/top_level.txt
metronome/__init__.py
metronome/client.py
metronome/exceptions.py
metronome/models/__init__.py
metronome/models/metronome_pb2.py
